[
  {
    "package": "bigassertr",
    "oncran": true
  },
  {
    "package": "bigparallelr",
    "oncran": true
  },
  {
    "package": "bigreadr",
    "oncran": true
  },
  {
    "package": "bigsnpr"
  },
  {
    "package": "bigsparser",
    "oncran": true
  },
  {
    "package": "bigstatsr",
    "oncran": true
  },
  {
    "package": "bigutilsr",
    "oncran": true
  },
  {
    "package": "inplace",
    "oncran": true
  },
  {
    "package": "mmapcharr",
    "oncran": true
  },
  {
    "package": "primefactr",
    "oncran": true
  },
  {
    "package": "rmio",
    "oncran": true
  },
  {
    "package": "runonce",
    "oncran": true
  }
]
